xwire/transport/__init__.py
xwire/transport/_private/__init__.py
xwire/transport/_private/csv/__init__.py
xwire/transport/_private/csv/_deserialize.py
xwire/transport/_private/csv/_serialize.py
xwire/transport/_private/decorators/__init__.py
xwire/transport/_private/decorators/_serializable.py
xwire/transport/_private/exceptions/__init__.py
xwire/transport/_private/exceptions/_exceptions.py
xwire/transport/_private/json/__init__.py
xwire/transport/_private/json/_deserialize.py
xwire/transport/_private/json/_serialize.py
xwire/transport/public/__init__.py
xwire/transport/public/csv.py
xwire/transport/public/json.py
xwire.transport-0.1.13.dist-info/WHEEL
xwire.transport-0.1.13.dist-info/METADATA
xwire.transport-0.1.13.dist-info/RECORD
