Metadata-Version: 2.1
Name: xwire.transport
Version: 0.1.13
Summary: 
Author: tylerlaberge
Author-email: tylerlaberge@protonmail.com
Requires-Python: >=3.8,<4.0
Classifier: Programming Language :: Python :: 3
Classifier: Programming Language :: Python :: 3.8
Classifier: Programming Language :: Python :: 3.9
Requires-Dist: xwire.common (>=0.1.0,<0.2.0)
